botbase/__init__.py
botbase/botbase.py
botbase/db/__init__.py
botbase/db/blacklist.py
botbase/db/commands.py
botbase/db/metadata.py
botbase/exts/blacklist.py
botbase/exts/log_commands.py
botbase/exts/log_guilds.py
botbase/models.py
botbase/py.typed
botbase/wraps/__init__.py
botbase/wraps/channel.py
botbase/wraps/inter.py
botbase/wraps/member.py
botbase/wraps/thread.py
botbase/wraps/user.py
botbase/wraps/wrap.py
ooliver_botbase-2.0.3.dist-info/METADATA
ooliver_botbase-2.0.3.dist-info/WHEEL
ooliver_botbase-2.0.3.dist-info/RECORD
